{
  "tableName": "realtime_ethereum_mainnet_block_headers_REALTIME",
  "tableType": "REALTIME",
  "segmentsConfig": {
    "timeColumnName": "timestamp",
    "timeType": "MILLISECONDS",
    "replication": "{{ .PinotSegmentsReplication }}",
    "retentionTimeUnit": "DAYS",
    "retentionTimeValue": "7",
    "deletedSegmentsRetentionPeriod": "1d",
    "replicasPerPartition": "1"
  },
  "tenants": {
    "broker": "{{ .PinotTenantBroker }}",
    "server": "{{ .PinotTenantServer }}"
  },
  "tableIndexConfig": {
    "rangeIndexVersion": 2,
    "autoGeneratedInvertedIndex": false,
    "varLengthDictionaryColumns": ["parent_hash"],
    "noDictionaryColumns": ["hash"],
    "createInvertedIndexDuringSegmentGeneration": false,
    "loadMode": "MMAP",
    "enableDefaultStarTree": false,
    "tierOverwrites": {
      "hotTier": {
        "starTreeIndexConfigs": null
      },
      "coldTier": {
        "starTreeIndexConfigs": null
      }
    },
    "enableDynamicStarTreeCreation": false,
    "aggregateMetrics": false,
    "nullHandlingEnabled": false,
    "columnMajorSegmentBuilderEnabled": false,
    "optimizeDictionary": false,
    "optimizeDictionaryForMetrics": false,
    "noDictionarySizeRatioThreshold": 0.85,
    "sortedColumn": [
      "number"
    ]
  },
  "metadata": {
    "customConfigs": {
      "customKey": "customValue"
    }
  },
  "fieldConfigList": [
    {
      "name": "number",
      "encodingType": "RAW",
      "indexType": "SORTED",
      "indexTypes": [
        "SORTED"
      ],
      "timestampConfig": {},
      "indexes": {
        "inverted": {
          "enabled": "true"
        }
      },
      "tierOverwrites": null
    }
  ],
  "ingestionConfig": {
    "segmentTimeValueCheck": true,
    "streamIngestionConfig": {
      "streamConfigMaps": [
        {
          "streamType": "kafka",
          "stream.kafka.consumer.type": "high-level",
          "stream.kafka.topic.name": "{{ .KafkaTopic }}",
          "stream.kafka.decoder.class.name": "org.apache.pinot.plugin.stream.kafka.KafkaJSONMessageDecoder",
          "stream.kafka.consumer.factory.class.name": "org.apache.pinot.plugin.stream.kafka20.KafkaConsumerFactory",
          "stream.kafka.broker.list": "kafka:9092",
          "stream.kafka.consumer.prop.auto.offset.reset": "smallest",
          "stream.kafka.decoder.prop.schema.registry.rest.url": "http://schema-registry:8081",
          "stream.kafka.decoder.prop.schema.registry.schema.name": "ethereum_mainnet_block_headers-value",
          "stream.kafka.decoder.prop.schema.registry.schema.version": "latest"
        }
      ],
      "columnMajorSegmentBuilderEnabled": false
    },
    "continueOnError": true,
    "rowTimeValueCheck": true,
    "transformConfigs": [
      {
        "columnName": "hash_json",
        "transformFunction": "json_format(hash)"
      }
    ]
  },
  "tierConfigs": [
    {
      "name": "hotTier",
      "segmentSelectorType": "time",
      "segmentAge": "3130d",
      "storageType": "pinot_server",
      "serverTag": "DefaultTenant_REALTIME"
    }
  ],
  "isDimTable": false,
  "routing":{
    "segmentPrunerTypes": [
      "partition"
    ],
    "instanceSelectorType": "strictReplicaGroup"
  }
}